README.md
setup.py
argvee/__init__.py
argvee/app.py
argvee.egg-info/PKG-INFO
argvee.egg-info/SOURCES.txt
argvee.egg-info/dependency_links.txt
argvee.egg-info/top_level.txt