Metadata-Version: 1.1
Name: argvee
Version: 0.4.5
Summary: Easily parse command line argument by virtue of the functions defined in the module
Home-page: https://bitbucket.org/johannestaas/argvee
Author: Johan Nestaas
Author-email: johannestaas@gmail.com
License: GPLv3+
Keywords: python programming argv argument parsing
Platform: UNKNOWN
Classifier: Development Status :: 4 - Beta
Classifier: License :: OSI Approved :: GNU General Public License v3 or later (GPLv3+)
Classifier: Environment :: Console
Classifier: Environment :: X11 Applications :: Qt
Classifier: Environment :: MacOS X
Classifier: Environment :: Win32 (MS Windows)
Classifier: Operating System :: POSIX
Classifier: Operating System :: MacOS :: MacOS X
Classifier: Operating System :: Microsoft :: Windows
Classifier: Programming Language :: Python
